harlequin_clickhouse/__init__.py
harlequin_clickhouse/adapter.py
harlequin_clickhouse/cli_options.py
harlequin_clickhouse/py.typed
harlequin_clickhouse_adapter-0.1.2.dist-info/METADATA
harlequin_clickhouse_adapter-0.1.2.dist-info/WHEEL
harlequin_clickhouse_adapter-0.1.2.dist-info/entry_points.txt
harlequin_clickhouse_adapter-0.1.2.dist-info/licenses/LICENSE
harlequin_clickhouse_adapter-0.1.2.dist-info/RECORD
