Metadata-Version: 2.4
Name: harlequin-clickhouse-adapter
Version: 0.1.2
Summary: A Harlequin adapter for ClickHouse.
Author: Artem Gromov
License-File: LICENSE
Requires-Python: <4.0,>=3.8.1
Requires-Dist: clickhouse-driver>=0.2.6
Requires-Dist: harlequin<3,>=1.7
